rest_framework_miem/__init__.py
rest_framework_miem/serializers.py
django_rest_inherits_error_messages-1.0.0.dist-info/METADATA
django_rest_inherits_error_messages-1.0.0.dist-info/WHEEL
django_rest_inherits_error_messages-1.0.0.dist-info/top_level.txt
django_rest_inherits_error_messages-1.0.0.dist-info/RECORD
