Metadata-Version: 2.1
Name: django-rest-inherits-error-messages
Version: 1.0.0
Summary: ModelSerializer inherits the error_messages of the model
Home-page: https://github.com/gongul/django-rest-inherits-error-messages
Author: gongul
Author-email: projectgongul@gmail.com
License: MIT
Platform: UNKNOWN
Classifier: Environment :: Web Environment
Classifier: Framework :: Django
Classifier: Intended Audience :: Developers
Classifier: Intended Audience :: System Administrators
Classifier: Operating System :: OS Independent
Classifier: Topic :: Internet
Classifier: Topic :: Internet :: WWW/HTTP
Classifier: Programming Language :: Python
Classifier: Programming Language :: Python :: 3
Classifier: License :: OSI Approved :: MIT License
Requires-Dist: Django (>=1.8.0)
Requires-Dist: djangorestframework (>=3.1.3)
